odoo8_addon_github_connector-8.0.0.0.0.99.dev2-py2.7-nspkg.pth
odoo_addons/github_connector/__openerp__.py
odoo_addons/github_connector/__init__.py
odoo_addons/github_connector/README.rst
odoo_addons/github_connector/security/ir.model.access.csv
odoo_addons/github_connector/models/github_comment.py
odoo_addons/github_connector/models/github_team.py
odoo_addons/github_connector/models/abstract_github_model_author.py
odoo_addons/github_connector/models/abstract_github_model.py
odoo_addons/github_connector/models/wizard_update_from_github.py
odoo_addons/github_connector/models/res_partner.py
odoo_addons/github_connector/models/github_repository_branch.py
odoo_addons/github_connector/models/wizard_download_analyze_branch.py
odoo_addons/github_connector/models/git_author.py
odoo_addons/github_connector/models/github_repository.py
odoo_addons/github_connector/models/github_issue.py
odoo_addons/github_connector/models/__init__.py
odoo_addons/github_connector/models/git_commit.py
odoo_addons/github_connector/models/github_organization_serie.py
odoo_addons/github_connector/models/ir_values.py
odoo_addons/github_connector/models/wizard_load_github_model.py
odoo_addons/github_connector/models/github_organization.py
odoo_addons/github_connector/models/wizard_update_company_author.py
odoo_addons/github_connector/models/github.py
odoo_addons/github_connector/views/view_wizard_download_analyze_branch.xml
odoo_addons/github_connector/views/view_github_organization.xml
odoo_addons/github_connector/views/view_wizard_load_github_model.xml
odoo_addons/github_connector/views/view_git_commit.xml
odoo_addons/github_connector/views/view_git_author.xml
odoo_addons/github_connector/views/action.xml
odoo_addons/github_connector/views/menu.xml
odoo_addons/github_connector/views/view_github_issue.xml
odoo_addons/github_connector/views/view_github_team.xml
odoo_addons/github_connector/views/view_github_repository_branch.xml
odoo8_addon_github_connector-8.0.0.0.0.99.dev2.dist-info/top_level.txt
odoo8_addon_github_connector-8.0.0.0.0.99.dev2.dist-info/WHEEL
odoo8_addon_github_connector-8.0.0.0.0.99.dev2.dist-info/RECORD
odoo8_addon_github_connector-8.0.0.0.0.99.dev2.dist-info/metadata.json
odoo8_addon_github_connector-8.0.0.0.0.99.dev2.dist-info/DESCRIPTION.rst
odoo8_addon_github_connector-8.0.0.0.0.99.dev2.dist-info/METADATA
odoo8_addon_github_connector-8.0.0.0.0.99.dev2.dist-info/namespace_packages.txt
