Metadata-Version: 2.0
Name: odoo8-addon-github-connector
Version: 8.0.0.0.0.99.dev2
Summary: Recover information from github repositories
Home-page: UNKNOWN
Author: UNKNOWN
Author-email: UNKNOWN
License: UNKNOWN
Platform: UNKNOWN
Requires-Dist: git
Requires-Dist: markdown
Requires-Dist: odoo (<9.0a,>=8.0a)
Classifier: Programming Language :: Python :: 2.7
Classifier: Framework :: Odoo
